fasthistpak/__init__.py
fasthistpak/fasthist.py
fasthistpak-0.0.1.dist-info/METADATA
fasthistpak-0.0.1.dist-info/WHEEL
fasthistpak-0.0.1.dist-info/top_level.txt
fasthistpak-0.0.1.dist-info/RECORD
